HISTORY.rst
LICENSE
MANIFEST.in
README.rst
setup.py
attrs/__init__.py
attrs/admin.py
attrs/forms.py
attrs/models.py
attrs/tables.py
attrs/tests.py
attrs/urls.py
attrs/utils.py
attrs/views.py
attrs/migrations/0001_initial.py
attrs/migrations/__init__.py
django_attrs.egg-info/PKG-INFO
django_attrs.egg-info/SOURCES.txt
django_attrs.egg-info/dependency_links.txt
django_attrs.egg-info/not-zip-safe
django_attrs.egg-info/requires.txt
django_attrs.egg-info/top_level.txt