Metadata-Version: 1.1
Name: django-attrs
Version: 0.1.1
Summary: EAV for Django using JSONField
Home-page: https://github.com/zostera/django-attrs
Author: Dylan Verheul
Author-email: dylan@zostera.nl
License: MIT License
Keywords: django-attrs
Platform: UNKNOWN
Classifier: Development Status :: 2 - Pre-Alpha
Classifier: Intended Audience :: Developers
Classifier: License :: OSI Approved :: MIT License
Classifier: Programming Language :: Python :: 2
Classifier: Programming Language :: Python :: 2.6
Classifier: Programming Language :: Python :: 2.7
Classifier: Programming Language :: Python :: 3
Classifier: Programming Language :: Python :: 3.3
Classifier: Operating System :: OS Independent
Classifier: Topic :: Software Development :: Libraries
Classifier: Topic :: Utilities
Classifier: Environment :: Web Environment
Classifier: Framework :: Django
